cognite/client/__init__.py
cognite/client/_api/__init__.py
cognite/client/_api/agents/__init__.py
cognite/client/_api/agents/agents.py
cognite/client/_api/ai/__init__.py
cognite/client/_api/ai/tools/__init__.py
cognite/client/_api/ai/tools/documents.py
cognite/client/_api/annotations.py
cognite/client/_api/assets.py
cognite/client/_api/data_modeling/__init__.py
cognite/client/_api/data_modeling/containers.py
cognite/client/_api/data_modeling/data_models.py
cognite/client/_api/data_modeling/graphql.py
cognite/client/_api/data_modeling/instances.py
cognite/client/_api/data_modeling/space_statistics.py
cognite/client/_api/data_modeling/spaces.py
cognite/client/_api/data_modeling/statistics.py
cognite/client/_api/data_modeling/views.py
cognite/client/_api/data_sets.py
cognite/client/_api/datapoint_tasks.py
cognite/client/_api/datapoints.py
cognite/client/_api/datapoints_subscriptions.py
cognite/client/_api/diagrams.py
cognite/client/_api/document_preview.py
cognite/client/_api/documents.py
cognite/client/_api/entity_matching.py
cognite/client/_api/events.py
cognite/client/_api/extractionpipelines.py
cognite/client/_api/files.py
cognite/client/_api/functions/__init__.py
cognite/client/_api/functions/calls.py
cognite/client/_api/functions/schedules.py
cognite/client/_api/geospatial.py
cognite/client/_api/hosted_extractors/__init__.py
cognite/client/_api/hosted_extractors/destinations.py
cognite/client/_api/hosted_extractors/jobs.py
cognite/client/_api/hosted_extractors/mappings.py
cognite/client/_api/hosted_extractors/sources.py
cognite/client/_api/iam/__init__.py
cognite/client/_api/iam/groups.py
cognite/client/_api/iam/security_categories.py
cognite/client/_api/iam/sessions.py
cognite/client/_api/iam/token.py
cognite/client/_api/labels.py
cognite/client/_api/org_apis/principals.py
cognite/client/_api/postgres_gateway/__init__.py
cognite/client/_api/postgres_gateway/tables.py
cognite/client/_api/postgres_gateway/users.py
cognite/client/_api/raw/__init__.py
cognite_sdk-7.91.0.dist-info/licenses/LICENSE
cognite_sdk-7.91.0.dist-info/METADATA
cognite_sdk-7.91.0.dist-info/WHEEL
cognite_sdk-7.91.0.dist-info/RECORD
