Metadata-Version: 2.4
Name: cognite-sdk
Version: 7.91.0
Summary: Cognite Python SDK
License: Apache-2.0
License-File: LICENSE
Author: Erlend Vollset
Author-email: erlend.vollset@cognite.com
Requires-Python: >=3.10,<4.0
Classifier: License :: OSI Approved :: Apache Software License
Classifier: Programming Language :: Python :: 3
Classifier: Programming Language :: Python :: 3.10
Classifier: Programming Language :: Python :: 3.11
Classifier: Programming Language :: Python :: 3.12
Classifier: Programming Language :: Python :: 3.13
Classifier: Programming Language :: Python :: 3.14
Provides-Extra: all
Provides-Extra: functions
Provides-Extra: geo
Provides-Extra: numpy
Provides-Extra: pandas
Provides-Extra: pyodide
Provides-Extra: sympy
Provides-Extra: yaml
Requires-Dist: PyYAML (>=6.0,<7.0) ; extra == "yaml" or extra == "all"
Requires-Dist: geopandas (>=0.14) ; extra == "geo" or extra == "all"
Requires-Dist: msal (>=1.31,<2.0)
Requires-Dist: numpy (>=1.25) ; extra == "numpy" or extra == "all"
Requires-Dist: packaging (>=20)
Requires-Dist: pandas (>=2.1) ; extra == "pandas" or extra == "all"
Requires-Dist: pip (>=20.0.0) ; extra == "functions" or extra == "all"
Requires-Dist: protobuf (>=4)
Requires-Dist: pyodide-http (>=0.2.1,<0.3.0) ; extra == "pyodide"
Requires-Dist: requests (>=2.27,<3.0)
Requires-Dist: requests_oauthlib (>=1,<2)
Requires-Dist: shapely (>=1.7.0) ; extra == "geo" or extra == "all"
Requires-Dist: sympy ; extra == "sympy" or extra == "all"
Requires-Dist: typing_extensions (>=4)
Requires-Dist: tzdata (>=2024.1) ; (platform_system == "Windows" or platform_system == "Emscripten") and (extra == "pyodide")
Project-URL: Documentation, https://cognite-sdk-python.readthedocs-hosted.com
